pii_scanner/__init__.py
pii_scanner/scanner.py
pii_scanner/check_digit_warehouse/__init__.py
pii_scanner/check_digit_warehouse/checker.py
pii_scanner/check_digit_warehouse/validate_entity_type.py
pii_scanner/check_digit_warehouse/validators.py
pii_scanner/check_digit_warehouse/verification_required_list.py
pii_scanner/constants/__init__.py
pii_scanner/constants/patterns_countries.py
pii_scanner/file_readers/__init__.py
pii_scanner/file_readers/csv_reader.py
pii_scanner/file_readers/doc_reader.py
pii_scanner/file_readers/json_reader.py
pii_scanner/file_readers/process_column.py
pii_scanner/file_readers/xlsx_reader.py
pii_scanner/octopii/__init__.py
pii_scanner/octopii/file_utils.py
pii_scanner/octopii/image_utils.py
pii_scanner/octopii/octopii.py
pii_scanner/octopii/octopii_pii_detector.py
pii_scanner/octopii/text_utils.py
pii_scanner/octopii/files_store/definitions.json
pii_scanner/octopii/files_store/face_cascade.xml
pii_scanner/regex_patterns/__init__.py
pii_scanner/regex_patterns/matcher_patterns.py
pii_scanner/regex_patterns/presidio_patterns.py
pii_scanner/scanners/__init__.py
pii_scanner/scanners/ner_scanner.py
pii_scanner/scanners/spacy_matcher_scanner.py
pii_scanner/utils/__init__.py
pii_scanner/utils/csv_file.py
pii_scanner/utils/json_file.py
pii_scanner/utils/preprocess_text_nlp.py
pii_scanner/utils/xlsx_file.py
pii_Scanner-0.1.22.dist-info/METADATA
pii_Scanner-0.1.22.dist-info/WHEEL
pii_Scanner-0.1.22.dist-info/top_level.txt
pii_Scanner-0.1.22.dist-info/RECORD
