Metadata-Version: 2.1
Name: pii-Scanner
Version: 0.1.22
Summary: A library for scanning Personally Identifiable Information (PII).
Home-page: https://github.com/devankit01/pii_scanner
Author: Ankit Gupta
Author-email: devankitgupta01@gmail.com
Classifier: Programming Language :: Python :: 3
Classifier: License :: OSI Approved :: MIT License
Classifier: Operating System :: OS Independent
Requires-Python: >=3.10
Requires-Dist: presidio-analyzer==2.2.32
Requires-Dist: openpyxl==3.1.5
Requires-Dist: pydantic==2.10.3
Requires-Dist: numpy==2.0.2
Requires-Dist: unstructured[docx,pptx]
Requires-Dist: unstructured[pdf]
Requires-Dist: python-stdnum==1.20
Requires-Dist: pytesseract==0.3.13
Requires-Dist: PyPDF2==3.0.1
Requires-Dist: xmltodict==0.14.2
Requires-Dist: scikit-image==0.25.1
Requires-Dist: deskew==1.5.1
